{
 "cells": [
  {
   "cell_type": "markdown",
   "metadata": {
    "slideshow": {
     "slide_type": "slide"
    }
   },
   "source": [
    "# Meta programming?"
   ]
  },
  {
   "cell_type": "markdown",
   "metadata": {},
   "source": [
    "Cycle some function (or class) types to decide what to do"
   ]
  },
  {
   "cell_type": "code",
   "execution_count": 15,
   "metadata": {},
   "outputs": [],
   "source": [
    "# __annotations__ "
   ]
  },
  {
   "cell_type": "code",
   "execution_count": 16,
   "metadata": {
    "collapsed": true
   },
   "outputs": [],
   "source": [
    "def test(name: str):\n",
    "    print(name)"
   ]
  },
  {
   "cell_type": "code",
   "execution_count": 17,
   "metadata": {},
   "outputs": [
    {
     "data": {
      "text/plain": [
       "{'name': str}"
      ]
     },
     "execution_count": 17,
     "metadata": {},
     "output_type": "execute_result"
    }
   ],
   "source": [
    "test.__annotations__"
   ]
  },
  {
   "cell_type": "code",
   "execution_count": 23,
   "metadata": {
    "collapsed": true
   },
   "outputs": [],
   "source": [
    "def test(name: str, test: int):\n",
    "    print(name, test)"
   ]
  },
  {
   "cell_type": "code",
   "execution_count": 19,
   "metadata": {},
   "outputs": [
    {
     "data": {
      "text/plain": [
       "{'name': str, 'test': int}"
      ]
     },
     "execution_count": 19,
     "metadata": {},
     "output_type": "execute_result"
    }
   ],
   "source": [
    "test.__annotations__"
   ]
  },
  {
   "cell_type": "code",
   "execution_count": 21,
   "metadata": {
    "collapsed": true
   },
   "outputs": [],
   "source": [
    "from typing import List\n",
    "def test(name: str, test: List[int]):\n",
    "    print(name, test)"
   ]
  },
  {
   "cell_type": "code",
   "execution_count": 22,
   "metadata": {},
   "outputs": [
    {
     "data": {
      "text/plain": [
       "{'name': str, 'test': typing.List[int]}"
      ]
     },
     "execution_count": 22,
     "metadata": {},
     "output_type": "execute_result"
    }
   ],
   "source": [
    "test.__annotations__"
   ]
  },
  {
   "cell_type": "code",
   "execution_count": 24,
   "metadata": {
    "collapsed": true
   },
   "outputs": [],
   "source": [
    "def test(name: str, test: List[int]) -> int:\n",
    "    print(name, test)\n",
    "    return 0"
   ]
  },
  {
   "cell_type": "code",
   "execution_count": 25,
   "metadata": {},
   "outputs": [
    {
     "data": {
      "text/plain": [
       "{'name': str, 'return': int, 'test': typing.List[int]}"
      ]
     },
     "execution_count": 25,
     "metadata": {},
     "output_type": "execute_result"
    }
   ],
   "source": [
    "test.__annotations__"
   ]
  },
  {
   "cell_type": "markdown",
   "metadata": {
    "slideshow": {
     "slide_type": "slide"
    }
   },
   "source": [
    "# Disassembling"
   ]
  },
  {
   "cell_type": "markdown",
   "metadata": {
    "slideshow": {
     "slide_type": "subslide"
    }
   },
   "source": [
    "<small>\n",
    "src: https://www.getdrip.com/deliveries/cvxdqhqopuxpws94ayrx?__s=ug11p5y75reem5tszuoo\n",
    "</small>\n"
   ]
  },
  {
   "cell_type": "code",
   "execution_count": 1,
   "metadata": {
    "collapsed": true
   },
   "outputs": [],
   "source": [
    "def greet(name):\n",
    "    return 'Hello, ' + name + '!'"
   ]
  },
  {
   "cell_type": "code",
   "execution_count": 2,
   "metadata": {},
   "outputs": [
    {
     "data": {
      "text/plain": [
       "'Hello, Dan!'"
      ]
     },
     "execution_count": 2,
     "metadata": {},
     "output_type": "execute_result"
    }
   ],
   "source": [
    "greet('Dan')"
   ]
  },
  {
   "cell_type": "code",
   "execution_count": 3,
   "metadata": {
    "collapsed": true
   },
   "outputs": [],
   "source": [
    "import dis"
   ]
  },
  {
   "cell_type": "code",
   "execution_count": 4,
   "metadata": {},
   "outputs": [
    {
     "name": "stdout",
     "output_type": "stream",
     "text": [
      "  2           0 LOAD_CONST               1 ('Hello, ')\n",
      "              2 LOAD_FAST                0 (name)\n",
      "              4 BINARY_ADD\n",
      "              6 LOAD_CONST               2 ('!')\n",
      "              8 BINARY_ADD\n",
      "             10 RETURN_VALUE\n"
     ]
    }
   ],
   "source": [
    "dis.dis(greet)"
   ]
  },
  {
   "cell_type": "code",
   "execution_count": 7,
   "metadata": {
    "collapsed": true
   },
   "outputs": [],
   "source": [
    "def explode(name):\n",
    "    \n",
    "    for char in name:\n",
    "        print(char)\n",
    "        \n",
    "    return list(name)"
   ]
  },
  {
   "cell_type": "code",
   "execution_count": 8,
   "metadata": {},
   "outputs": [
    {
     "name": "stdout",
     "output_type": "stream",
     "text": [
      "D\n",
      "a\n",
      "n\n"
     ]
    },
    {
     "data": {
      "text/plain": [
       "['D', 'a', 'n']"
      ]
     },
     "execution_count": 8,
     "metadata": {},
     "output_type": "execute_result"
    }
   ],
   "source": [
    "explode(\"Dan\")"
   ]
  },
  {
   "cell_type": "code",
   "execution_count": 9,
   "metadata": {},
   "outputs": [
    {
     "name": "stdout",
     "output_type": "stream",
     "text": [
      "  3           0 SETUP_LOOP              20 (to 22)\n",
      "              2 LOAD_FAST                0 (name)\n",
      "              4 GET_ITER\n",
      "        >>    6 FOR_ITER                12 (to 20)\n",
      "              8 STORE_FAST               1 (char)\n",
      "\n",
      "  4          10 LOAD_GLOBAL              0 (print)\n",
      "             12 LOAD_FAST                1 (char)\n",
      "             14 CALL_FUNCTION            1\n",
      "             16 POP_TOP\n",
      "             18 JUMP_ABSOLUTE            6\n",
      "        >>   20 POP_BLOCK\n",
      "\n",
      "  6     >>   22 LOAD_GLOBAL              1 (list)\n",
      "             24 LOAD_FAST                0 (name)\n",
      "             26 CALL_FUNCTION            1\n",
      "             28 RETURN_VALUE\n"
     ]
    }
   ],
   "source": [
    "dis.dis(explode)"
   ]
  },
  {
   "cell_type": "code",
   "execution_count": 5,
   "metadata": {
    "collapsed": true,
    "slideshow": {
     "slide_type": "-"
    }
   },
   "outputs": [],
   "source": [
    "def apply_some_function_to_a_number(func):\n",
    "    def wrapper(x):            \n",
    "        y = random.randint(1, 10)\n",
    "        print(\"x: %s ^ y: %s\" % (x, y))\n",
    "        return func(x, y)\n",
    "    return wrapper"
   ]
  },
  {
   "cell_type": "code",
   "execution_count": 6,
   "metadata": {},
   "outputs": [
    {
     "name": "stdout",
     "output_type": "stream",
     "text": [
      "  2           0 LOAD_CLOSURE             0 (func)\n",
      "              2 BUILD_TUPLE              1\n",
      "              4 LOAD_CONST               1 (<code object wrapper at 0x7fd378a5b8a0, file \"<ipython-input-5-91e3a6b23e2d>\", line 2>)\n",
      "              6 LOAD_CONST               2 ('apply_some_function_to_a_number.<locals>.wrapper')\n",
      "              8 MAKE_FUNCTION            8\n",
      "             10 STORE_FAST               1 (wrapper)\n",
      "\n",
      "  6          12 LOAD_FAST                1 (wrapper)\n",
      "             14 RETURN_VALUE\n"
     ]
    }
   ],
   "source": [
    "dis.dis(apply_some_function_to_a_number)"
   ]
  },
  {
   "cell_type": "code",
   "execution_count": 11,
   "metadata": {},
   "outputs": [
    {
     "ename": "TypeError",
     "evalue": "unsupported operand type(s) for +: 'int' and 'str'",
     "output_type": "error",
     "traceback": [
      "\u001b[0;31m---------------------------------------------------------------------------\u001b[0m",
      "\u001b[0;31mTypeError\u001b[0m                                 Traceback (most recent call last)",
      "\u001b[0;32m<ipython-input-11-e0ba07a0ab2a>\u001b[0m in \u001b[0;36m<module>\u001b[0;34m()\u001b[0m\n\u001b[1;32m      1\u001b[0m \u001b[0;32mfor\u001b[0m \u001b[0ma\u001b[0m \u001b[0;32min\u001b[0m \u001b[0;34m[\u001b[0m\u001b[0;34m'a'\u001b[0m\u001b[0;34m,\u001b[0m \u001b[0;34m\"test\"\u001b[0m\u001b[0;34m,\u001b[0m \u001b[0;36m1\u001b[0m\u001b[0;34m,\u001b[0m \u001b[0;32mFalse\u001b[0m\u001b[0;34m]\u001b[0m\u001b[0;34m:\u001b[0m\u001b[0;34m\u001b[0m\u001b[0m\n\u001b[0;32m----> 2\u001b[0;31m     \u001b[0ma\u001b[0m \u001b[0;34m+\u001b[0m \u001b[0;34m'string'\u001b[0m\u001b[0;34m\u001b[0m\u001b[0m\n\u001b[0m",
      "\u001b[0;31mTypeError\u001b[0m: unsupported operand type(s) for +: 'int' and 'str'"
     ]
    }
   ],
   "source": [
    "for a in ['a', \"test\", 1, False]:\n",
    "    a + 'string'"
   ]
  },
  {
   "cell_type": "code",
   "execution_count": 13,
   "metadata": {},
   "outputs": [
    {
     "name": "stdout",
     "output_type": "stream",
     "text": [
      "  1           0 SETUP_LOOP              20 (to 22)\n",
      "              2 LOAD_CONST               6 (('a', 'test', 1, False))\n",
      "              4 GET_ITER\n",
      "        >>    6 FOR_ITER                12 (to 20)\n",
      "              8 STORE_NAME               0 (a)\n",
      "\n",
      "  2          10 LOAD_NAME                0 (a)\n",
      "             12 LOAD_CONST               4 ('string')\n",
      "    -->      14 BINARY_ADD\n",
      "             16 POP_TOP\n",
      "             18 JUMP_ABSOLUTE            6\n",
      "        >>   20 POP_BLOCK\n",
      "        >>   22 LOAD_CONST               5 (None)\n",
      "             24 RETURN_VALUE\n"
     ]
    }
   ],
   "source": [
    "# last traceback\n",
    "dis.dis()"
   ]
  },
  {
   "cell_type": "markdown",
   "metadata": {
    "slideshow": {
     "slide_type": "slide"
    }
   },
   "source": [
    "# Debugger"
   ]
  },
  {
   "cell_type": "markdown",
   "metadata": {
    "slideshow": {
     "slide_type": "subslide"
    }
   },
   "source": [
    "<small>\n",
    "src: https://github.com/spiside/pdb-tutorial\n",
    "</small>"
   ]
  }
 ],
 "metadata": {
  "celltoolbar": "Slideshow",
  "kernelspec": {
   "display_name": "Python 3",
   "language": "python",
   "name": "python3"
  },
  "language_info": {
   "codemirror_mode": {
    "name": "ipython",
    "version": 3
   },
   "file_extension": ".py",
   "mimetype": "text/x-python",
   "name": "python",
   "nbconvert_exporter": "python",
   "pygments_lexer": "ipython3",
   "version": "3.6.1"
  }
 },
 "nbformat": 4,
 "nbformat_minor": 2
}
